smi_ted/__init__.py
smi_ted/config.py
smi_ted/load.py
smi_ted/model.py
smi_ted/tokenizer.py
smi_ted-1.0.0.dist-info/licenses/LICENSE
smi_ted-1.0.0.dist-info/METADATA
smi_ted-1.0.0.dist-info/WHEEL
smi_ted-1.0.0.dist-info/top_level.txt
smi_ted-1.0.0.dist-info/RECORD
