Metadata-Version: 2.4
Name: smi-ted
Version: 1.0.0
Summary: SMILES-based Transformer Encoder-Decoder (SMI-TED)
Author: Eduardo Soares, Victor Shirasuna, Emilio Vital Brazil, Renato Cerqueira, Dmitry Zubarev, Kristin Schmidt
License:                                  Apache License
Project-URL: arxiv, https://arxiv.org/abs/2407.20267
Project-URL: homepage, https://huggingface.co/bisectgroup/materials-smi-ted-fork
Project-URL: repository, https://github.com/bisect-group/materials-smi-ted-fork
Project-URL: original_github, https://github.com/IBM/materials/tree/main/models/smi_ted
Project-URL: original_huggingface, https://huggingface.co/ibm/materials.smi-ted
Requires-Python: >=3.8
License-File: LICENSE
Requires-Dist: torch
Requires-Dist: transformers
Requires-Dist: pytorch-fast-transformers
Requires-Dist: rdkit
Requires-Dist: numpy
Dynamic: license-file
